[
  {
    "categoryId": 643,
    "categoryPrompt": "أفلام مصرية مشهورة (جديد) #603",
    "answer": "الفيل الازرق",
    "timestamp": "2026-02-21T18:03:08.004Z"
  },
  {
    "categoryId": 643,
    "categoryPrompt": "أفلام مصرية مشهورة (جديد) #603",
    "answer": "مفيه",
    "timestamp": "2026-02-21T18:03:09.023Z"
  },
  {
    "categoryId": 643,
    "categoryPrompt": "أفلام مصرية مشهورة (جديد) #603",
    "answer": "ولاد رزق",
    "timestamp": "2026-02-21T18:03:12.695Z"
  },
  {
    "categoryId": 643,
    "categoryPrompt": "أفلام مصرية مشهورة (جديد) #603",
    "answer": "En 3’ab el ot",
    "timestamp": "2026-02-21T18:03:13.114Z"
  },
  {
    "categoryId": 643,
    "categoryPrompt": "أفلام مصرية مشهورة (جديد) #603",
    "answer": "سيكو سيكو",
    "timestamp": "2026-02-21T18:03:19.967Z"
  },
  {
    "categoryId": 643,
    "categoryPrompt": "أفلام مصرية مشهورة (جديد) #603",
    "answer": "إن غاب الoat",
    "timestamp": "2026-02-21T18:03:21.201Z"
  },
  {
    "categoryId": 643,
    "categoryPrompt": "أفلام مصرية مشهورة (جديد) #603",
    "answer": "Siko siko",
    "timestamp": "2026-02-21T18:03:23.246Z"
  },
  {
    "categoryId": 813,
    "categoryPrompt": "أفلام كوميدي مصرية #773",
    "answer": "زكي شان",
    "timestamp": "2026-02-21T18:03:44.441Z"
  },
  {
    "categoryId": 813,
    "categoryPrompt": "أفلام كوميدي مصرية #773",
    "answer": "الناظر",
    "timestamp": "2026-02-21T18:03:45.364Z"
  },
  {
    "categoryId": 813,
    "categoryPrompt": "أفلام كوميدي مصرية #773",
    "answer": "عسل اسود",
    "timestamp": "2026-02-21T18:03:47.105Z"
  },
  {
    "categoryId": 813,
    "categoryPrompt": "أفلام كوميدي مصرية #773",
    "answer": "Zaki shan",
    "timestamp": "2026-02-21T18:03:49.460Z"
  },
  {
    "categoryId": 813,
    "categoryPrompt": "أفلام كوميدي مصرية #773",
    "answer": "مطب صناعي",
    "timestamp": "2026-02-21T18:03:55.193Z"
  },
  {
    "categoryId": 813,
    "categoryPrompt": "أفلام كوميدي مصرية #773",
    "answer": "‏بوحا",
    "timestamp": "2026-02-21T18:03:55.814Z"
  },
  {
    "categoryId": 813,
    "categoryPrompt": "أفلام كوميدي مصرية #773",
    "answer": "عوكل",
    "timestamp": "2026-02-21T18:03:59.187Z"
  },
  {
    "categoryId": 813,
    "categoryPrompt": "أفلام كوميدي مصرية #773",
    "answer": "اللمبي",
    "timestamp": "2026-02-21T18:04:02.565Z"
  },
  {
    "categoryId": 813,
    "categoryPrompt": "أفلام كوميدي مصرية #773",
    "answer": "اللمبى",
    "timestamp": "2026-02-21T18:04:03.094Z"
  },
  {
    "categoryId": 813,
    "categoryPrompt": "أفلام كوميدي مصرية #773",
    "answer": "لمبي",
    "timestamp": "2026-02-21T18:04:05.024Z"
  },
  {
    "categoryId": 813,
    "categoryPrompt": "أفلام كوميدي مصرية #773",
    "answer": "صعيدي فالجمعه",
    "timestamp": "2026-02-21T18:04:05.744Z"
  },
  {
    "categoryId": 861,
    "categoryPrompt": "أفلام مصرية مشهورة #821",
    "answer": "الناظر",
    "timestamp": "2026-02-21T18:04:35.033Z"
  },
  {
    "categoryId": 861,
    "categoryPrompt": "أفلام مصرية مشهورة #821",
    "answer": "كيره والجن",
    "timestamp": "2026-02-21T18:04:41.497Z"
  },
  {
    "categoryId": 861,
    "categoryPrompt": "أفلام مصرية مشهورة #821",
    "answer": "ملاكي الاسكندريa",
    "timestamp": "2026-02-21T18:04:43.941Z"
  },
  {
    "categoryId": 400,
    "categoryPrompt": "ممثليـن مصريين مشهورين - سهل #360",
    "answer": "عادل امام",
    "timestamp": "2026-02-21T18:05:18.042Z"
  },
  {
    "categoryId": 42,
    "categoryPrompt": "أفلام مصرية مشهورة في السعودية #2",
    "answer": "بوحه",
    "timestamp": "2026-02-21T18:06:20.101Z"
  },
  {
    "categoryId": 42,
    "categoryPrompt": "أفلام مصرية مشهورة في السعودية #2",
    "answer": "ولاد رزق",
    "timestamp": "2026-02-21T18:06:26.034Z"
  },
  {
    "categoryId": 42,
    "categoryPrompt": "أفلام مصرية مشهورة في السعودية #2",
    "answer": "فول الصين العظيم",
    "timestamp": "2026-02-21T18:06:37.916Z"
  },
  {
    "categoryId": 699,
    "categoryPrompt": "أفلام رومانسية مصرية (معروف) #659",
    "answer": "حبيبي",
    "timestamp": "2026-02-21T18:07:02.389Z"
  },
  {
    "categoryId": 699,
    "categoryPrompt": "أفلام رومانسية مصرية (معروف) #659",
    "answer": "زي الهوا",
    "timestamp": "2026-02-21T18:07:03.923Z"
  },
  {
    "categoryId": 699,
    "categoryPrompt": "أفلام رومانسية مصرية (معروف) #659",
    "answer": "عمر وسلمى",
    "timestamp": "2026-02-21T18:07:04.334Z"
  },
  {
    "categoryId": 699,
    "categoryPrompt": "أفلام رومانسية مصرية (معروف) #659",
    "answer": "اللمبي",
    "timestamp": "2026-02-21T18:07:12.628Z"
  },
  {
    "categoryId": 699,
    "categoryPrompt": "أفلام رومانسية مصرية (معروف) #659",
    "answer": "حبيبي انا",
    "timestamp": "2026-02-21T18:07:15.088Z"
  },
  {
    "categoryId": 699,
    "categoryPrompt": "أفلام رومانسية مصرية (معروف) #659",
    "answer": "كيره والجن",
    "timestamp": "2026-02-21T18:07:21.232Z"
  },
  {
    "categoryId": 699,
    "categoryPrompt": "أفلام رومانسية مصرية (معروف) #659",
    "answer": "سعر اللايالي",
    "timestamp": "2026-02-21T18:07:24.314Z"
  },
  {
    "categoryId": 699,
    "categoryPrompt": "أفلام رومانسية مصرية (معروف) #659",
    "answer": "بنات وسط البلد",
    "timestamp": "2026-02-21T18:07:25.227Z"
  },
  {
    "categoryId": 21,
    "categoryPrompt": "Best Pop Singers",
    "answer": "Bynoce",
    "timestamp": "2026-02-21T18:18:49.375Z"
  },
  {
    "categoryId": 21,
    "categoryPrompt": "Best Pop Singers",
    "answer": "Jonas",
    "timestamp": "2026-02-21T18:18:57.783Z"
  },
  {
    "categoryId": 13,
    "categoryPrompt": "Most Famous Actors of All Time",
    "answer": "Mathew",
    "timestamp": "2026-02-21T18:19:17.833Z"
  },
  {
    "categoryId": 18,
    "categoryPrompt": "Most Popular Singers Right Now",
    "answer": "Eminem",
    "timestamp": "2026-02-21T18:19:45.699Z"
  },
  {
    "categoryId": 18,
    "categoryPrompt": "Most Popular Singers Right Now",
    "answer": "Snoop dog",
    "timestamp": "2026-02-21T18:19:50.706Z"
  },
  {
    "categoryId": 18,
    "categoryPrompt": "Most Popular Singers Right Now",
    "answer": "Adle",
    "timestamp": "2026-02-21T18:19:53.592Z"
  },
  {
    "categoryId": 18,
    "categoryPrompt": "Most Popular Singers Right Now",
    "answer": "Byonce",
    "timestamp": "2026-02-21T18:19:59.717Z"
  },
  {
    "categoryId": 79,
    "categoryPrompt": "Popular New Year's Resolutions",
    "answer": "New me",
    "timestamp": "2026-02-21T18:20:17.227Z"
  },
  {
    "categoryId": 79,
    "categoryPrompt": "Popular New Year's Resolutions",
    "answer": "Pray",
    "timestamp": "2026-02-21T18:20:26.256Z"
  },
  {
    "categoryId": 2,
    "categoryPrompt": "Famous Horror Movies",
    "answer": "Grudge",
    "timestamp": "2026-02-21T18:20:43.033Z"
  },
  {
    "categoryId": 42,
    "categoryPrompt": "Famous Car Brands",
    "answer": "Kia",
    "timestamp": "2026-02-21T18:21:13.549Z"
  },
  {
    "categoryId": 42,
    "categoryPrompt": "Famous Car Brands",
    "answer": "Benz",
    "timestamp": "2026-02-21T18:21:16.227Z"
  },
  {
    "categoryId": 5,
    "categoryPrompt": "Best Sci-Fi Movies",
    "answer": "Avatar",
    "timestamp": "2026-02-21T18:22:49.706Z"
  },
  {
    "categoryId": 5,
    "categoryPrompt": "Best Sci-Fi Movies",
    "answer": "King kong",
    "timestamp": "2026-02-21T18:22:53.701Z"
  },
  {
    "categoryId": 5,
    "categoryPrompt": "Best Sci-Fi Movies",
    "answer": "Avengers",
    "timestamp": "2026-02-21T18:22:59.128Z"
  },
  {
    "categoryId": 5,
    "categoryPrompt": "Best Sci-Fi Movies",
    "answer": "Superman",
    "timestamp": "2026-02-21T18:23:01.594Z"
  },
  {
    "categoryId": 5,
    "categoryPrompt": "Best Sci-Fi Movies",
    "answer": "Spiderman",
    "timestamp": "2026-02-21T18:23:05.790Z"
  },
  {
    "categoryId": 5,
    "categoryPrompt": "Best Sci-Fi Movies",
    "answer": "Batman",
    "timestamp": "2026-02-21T18:23:08.342Z"
  },
  {
    "categoryId": 1,
    "categoryPrompt": "Best Movies of All Time",
    "answer": "Shawshang reedembtion",
    "timestamp": "2026-02-21T18:23:34.996Z"
  },
  {
    "categoryId": 61,
    "categoryPrompt": "Best Movie Franchises",
    "answer": "Avengers",
    "timestamp": "2026-02-21T18:24:06.515Z"
  },
  {
    "categoryId": 59,
    "categoryPrompt": "Best Pixar Movies",
    "answer": "Lego",
    "timestamp": "2026-02-21T18:24:34.056Z"
  },
  {
    "categoryId": 14,
    "categoryPrompt": "Famous Actresses",
    "answer": "Albatchino",
    "timestamp": "2026-02-21T18:25:08.160Z"
  },
  {
    "categoryId": 14,
    "categoryPrompt": "Famous Actresses",
    "answer": "Robert denaro",
    "timestamp": "2026-02-21T18:25:14.003Z"
  },
  {
    "categoryId": 14,
    "categoryPrompt": "Famous Actresses",
    "answer": "Dansel washinton",
    "timestamp": "2026-02-21T18:25:25.360Z"
  },
  {
    "categoryId": 7,
    "categoryPrompt": "Best Comedy Movies",
    "answer": "Men in black",
    "timestamp": "2026-02-21T18:26:29.876Z"
  },
  {
    "categoryId": 7,
    "categoryPrompt": "Best Comedy Movies",
    "answer": "Ride along",
    "timestamp": "2026-02-21T18:26:34.691Z"
  },
  {
    "categoryId": 7,
    "categoryPrompt": "Best Comedy Movies",
    "answer": "Rush hour",
    "timestamp": "2026-02-21T18:26:41.759Z"
  },
  {
    "categoryId": 7,
    "categoryPrompt": "Best Comedy Movies",
    "answer": "Bad boys",
    "timestamp": "2026-02-21T18:26:45.543Z"
  },
  {
    "categoryId": 7,
    "categoryPrompt": "Best Comedy Movies",
    "answer": "Wedding crashers",
    "timestamp": "2026-02-21T18:26:46.569Z"
  },
  {
    "categoryId": 18,
    "categoryPrompt": "Most Popular Singers Right Now",
    "answer": "Kendrick Lamar",
    "timestamp": "2026-02-21T18:28:09.514Z"
  },
  {
    "categoryId": 4,
    "categoryPrompt": "Best Superhero Movies",
    "answer": "Marvel",
    "timestamp": "2026-02-21T18:28:54.568Z"
  },
  {
    "categoryId": 29,
    "categoryPrompt": "Popular Snacks",
    "answer": "Lays",
    "timestamp": "2026-02-21T18:29:36.555Z"
  },
  {
    "categoryId": 29,
    "categoryPrompt": "Popular Snacks",
    "answer": "Snickers",
    "timestamp": "2026-02-21T18:29:37.272Z"
  },
  {
    "categoryId": 29,
    "categoryPrompt": "Popular Snacks",
    "answer": "Fries",
    "timestamp": "2026-02-21T18:29:37.885Z"
  },
  {
    "categoryId": 29,
    "categoryPrompt": "Popular Snacks",
    "answer": "Lay’s",
    "timestamp": "2026-02-21T18:29:40.340Z"
  },
  {
    "categoryId": 29,
    "categoryPrompt": "Popular Snacks",
    "answer": "Prongles",
    "timestamp": "2026-02-21T18:29:41.159Z"
  },
  {
    "categoryId": 29,
    "categoryPrompt": "Popular Snacks",
    "answer": "Kitkat",
    "timestamp": "2026-02-21T18:29:43.641Z"
  },
  {
    "categoryId": 29,
    "categoryPrompt": "Popular Snacks",
    "answer": "Pringles",
    "timestamp": "2026-02-21T18:29:44.232Z"
  },
  {
    "categoryId": 6,
    "categoryPrompt": "Best Romantic Movies",
    "answer": "Die hard",
    "timestamp": "2026-02-21T18:30:21.403Z"
  },
  {
    "categoryId": 11,
    "categoryPrompt": "Best Movies of the 2000s",
    "answer": "Shawshank",
    "timestamp": "2026-02-21T18:31:35.339Z"
  },
  {
    "categoryId": 44,
    "categoryPrompt": "Most Downloaded Apps Ever",
    "answer": "Teams",
    "timestamp": "2026-02-21T18:32:15.594Z"
  },
  {
    "categoryId": 80,
    "categoryPrompt": "Biggest Red Flags in a Person",
    "answer": "Lie",
    "timestamp": "2026-02-21T18:32:38.548Z"
  },
  {
    "categoryId": 80,
    "categoryPrompt": "Biggest Red Flags in a Person",
    "answer": "Late reply",
    "timestamp": "2026-02-21T18:32:40.166Z"
  },
  {
    "categoryId": 80,
    "categoryPrompt": "Biggest Red Flags in a Person",
    "answer": "Toxic",
    "timestamp": "2026-02-21T18:32:43.330Z"
  },
  {
    "categoryId": 80,
    "categoryPrompt": "Biggest Red Flags in a Person",
    "answer": "Mother",
    "timestamp": "2026-02-21T18:32:45.894Z"
  },
  {
    "categoryId": 80,
    "categoryPrompt": "Biggest Red Flags in a Person",
    "answer": "Goast",
    "timestamp": "2026-02-21T18:32:45.897Z"
  },
  {
    "categoryId": 80,
    "categoryPrompt": "Biggest Red Flags in a Person",
    "answer": "Aggressive",
    "timestamp": "2026-02-21T18:32:54.700Z"
  },
  {
    "categoryId": 80,
    "categoryPrompt": "Biggest Red Flags in a Person",
    "answer": "Hair",
    "timestamp": "2026-02-21T18:32:56.955Z"
  },
  {
    "categoryId": 80,
    "categoryPrompt": "Biggest Red Flags in a Person",
    "answer": "Body",
    "timestamp": "2026-02-21T18:33:00.537Z"
  },
  {
    "categoryId": 81,
    "categoryPrompt": "Things That Make People Happy",
    "answer": "Play",
    "timestamp": "2026-02-21T18:33:25.007Z"
  },
  {
    "categoryId": 81,
    "categoryPrompt": "Things That Make People Happy",
    "answer": "Sex",
    "timestamp": "2026-02-21T18:33:27.177Z"
  },
  {
    "categoryId": 81,
    "categoryPrompt": "Things That Make People Happy",
    "answer": "Gifts",
    "timestamp": "2026-02-21T18:33:28.611Z"
  },
  {
    "categoryId": 81,
    "categoryPrompt": "Things That Make People Happy",
    "answer": "Fuck",
    "timestamp": "2026-02-21T18:33:31.052Z"
  },
  {
    "categoryId": 81,
    "categoryPrompt": "Things That Make People Happy",
    "answer": "celebrate",
    "timestamp": "2026-02-21T18:33:33.506Z"
  },
  {
    "categoryId": 81,
    "categoryPrompt": "Things That Make People Happy",
    "answer": "Birthday",
    "timestamp": "2026-02-21T18:33:36.170Z"
  },
  {
    "categoryId": 81,
    "categoryPrompt": "Things That Make People Happy",
    "answer": "Appreciation",
    "timestamp": "2026-02-21T18:33:42.527Z"
  },
  {
    "categoryId": 50,
    "categoryPrompt": "Things in Your Kitchen",
    "answer": "Food",
    "timestamp": "2026-02-21T18:34:10.070Z"
  },
  {
    "categoryId": 52,
    "categoryPrompt": "Things in Your Bag",
    "answer": "Knife",
    "timestamp": "2026-02-21T18:34:37.917Z"
  },
  {
    "categoryId": 60,
    "categoryPrompt": "Famous Movie Villains",
    "answer": "Bane",
    "timestamp": "2026-02-21T18:35:28.814Z"
  },
  {
    "categoryId": 37,
    "categoryPrompt": "Best Cities to Visit",
    "answer": "Italy",
    "timestamp": "2026-02-21T18:35:52.694Z"
  },
  {
    "categoryId": 13,
    "categoryPrompt": "Most Famous Actors of All Time",
    "answer": "Dansiel Washington",
    "timestamp": "2026-02-21T18:45:06.266Z"
  },
  {
    "categoryId": 13,
    "categoryPrompt": "Most Famous Actors of All Time",
    "answer": "Lensrdo decaprio",
    "timestamp": "2026-02-21T18:45:12.511Z"
  },
  {
    "categoryId": 78,
    "categoryPrompt": "Best Olympic Sports to Watch",
    "answer": "Swim",
    "timestamp": "2026-02-21T18:46:00.956Z"
  },
  {
    "categoryId": 28,
    "categoryPrompt": "Most Popular Cuisines in the World",
    "answer": "Asian",
    "timestamp": "2026-02-21T18:46:51.741Z"
  },
  {
    "categoryId": 64,
    "categoryPrompt": "Best Luxury Watch Brands",
    "answer": "Ab",
    "timestamp": "2026-02-22T16:40:53.553Z"
  },
  {
    "categoryId": 64,
    "categoryPrompt": "Best Luxury Watch Brands",
    "answer": "Addidas",
    "timestamp": "2026-02-22T16:41:01.548Z"
  },
  {
    "categoryId": 11,
    "categoryPrompt": "Best Movies of the 2000s",
    "answer": "Tito",
    "timestamp": "2026-02-22T16:41:33.598Z"
  },
  {
    "categoryId": 11,
    "categoryPrompt": "Best Movies of the 2000s",
    "answer": "Shawshank redemption",
    "timestamp": "2026-02-22T16:41:38.520Z"
  },
  {
    "categoryId": 11,
    "categoryPrompt": "Best Movies of the 2000s",
    "answer": "Fight club",
    "timestamp": "2026-02-22T16:41:44.377Z"
  },
  {
    "categoryId": 11,
    "categoryPrompt": "Best Movies of the 2000s",
    "answer": "Interstellar",
    "timestamp": "2026-02-22T16:41:45.738Z"
  },
  {
    "categoryId": 11,
    "categoryPrompt": "Best Movies of the 2000s",
    "answer": "Kingkong",
    "timestamp": "2026-02-22T16:41:47.648Z"
  },
  {
    "categoryId": 15,
    "categoryPrompt": "Famous Movie Villains",
    "answer": "Penguin",
    "timestamp": "2026-02-22T16:42:17.672Z"
  },
  {
    "categoryId": 4,
    "categoryPrompt": "Best Superhero Movies",
    "answer": "Superman",
    "timestamp": "2026-02-22T16:42:59.238Z"
  },
  {
    "categoryId": 4,
    "categoryPrompt": "Best Superhero Movies",
    "answer": "Spider man",
    "timestamp": "2026-02-22T16:43:03.265Z"
  },
  {
    "categoryId": 27,
    "categoryPrompt": "Best Rappers of All Time",
    "answer": "Jcole",
    "timestamp": "2026-02-22T16:43:26.603Z"
  },
  {
    "categoryId": 27,
    "categoryPrompt": "Best Rappers of All Time",
    "answer": "Break",
    "timestamp": "2026-02-22T16:43:38.925Z"
  },
  {
    "categoryId": 27,
    "categoryPrompt": "Best Rappers of All Time",
    "answer": "Adam",
    "timestamp": "2026-02-22T16:43:45.755Z"
  },
  {
    "categoryId": 16,
    "categoryPrompt": "Best Movie Franchises",
    "answer": "Superman",
    "timestamp": "2026-02-22T16:44:12.711Z"
  },
  {
    "categoryId": 30,
    "categoryPrompt": "Best Songs of All Time",
    "answer": "Sky fall",
    "timestamp": "2026-02-22T16:44:31.297Z"
  },
  {
    "categoryId": 30,
    "categoryPrompt": "Best Songs of All Time",
    "answer": "Hello",
    "timestamp": "2026-02-22T16:44:35.283Z"
  },
  {
    "categoryId": 30,
    "categoryPrompt": "Best Songs of All Time",
    "answer": "Those where the days",
    "timestamp": "2026-02-22T16:44:38.292Z"
  },
  {
    "categoryId": 30,
    "categoryPrompt": "Best Songs of All Time",
    "answer": "Lonely",
    "timestamp": "2026-02-22T16:44:43.579Z"
  },
  {
    "categoryId": 30,
    "categoryPrompt": "Best Songs of All Time",
    "answer": "Love",
    "timestamp": "2026-02-22T16:44:44.421Z"
  },
  {
    "categoryId": 30,
    "categoryPrompt": "Best Songs of All Time",
    "answer": "Love of my life",
    "timestamp": "2026-02-22T16:44:49.578Z"
  },
  {
    "categoryId": 30,
    "categoryPrompt": "Best Songs of All Time",
    "answer": "Sway",
    "timestamp": "2026-02-22T16:44:50.765Z"
  },
  {
    "categoryId": 30,
    "categoryPrompt": "Best Songs of All Time",
    "answer": "Somebody that i used tot know",
    "timestamp": "2026-02-22T16:44:51.365Z"
  },
  {
    "categoryId": 30,
    "categoryPrompt": "Best Songs of All Time",
    "answer": "Life",
    "timestamp": "2026-02-22T16:44:52.192Z"
  },
  {
    "categoryId": 35,
    "categoryPrompt": "Breakfast Foods",
    "answer": "Beans",
    "timestamp": "2026-02-22T16:45:09.097Z"
  },
  {
    "categoryId": 35,
    "categoryPrompt": "Breakfast Foods",
    "answer": "Falafel",
    "timestamp": "2026-02-22T16:45:11.913Z"
  },
  {
    "categoryId": 35,
    "categoryPrompt": "Breakfast Foods",
    "answer": "Corn flakes",
    "timestamp": "2026-02-22T16:45:16.628Z"
  },
  {
    "categoryId": 46,
    "categoryPrompt": "Best NBA Players of All Time",
    "answer": "Samy",
    "timestamp": "2026-02-22T16:45:36.325Z"
  },
  {
    "categoryId": 78,
    "categoryPrompt": "Things in Your Bathroom",
    "answer": "Boobs",
    "timestamp": "2026-02-22T16:49:40.030Z"
  },
  {
    "categoryId": 78,
    "categoryPrompt": "Things in Your Bathroom",
    "answer": "Boob",
    "timestamp": "2026-02-22T16:49:42.939Z"
  },
  {
    "categoryId": 78,
    "categoryPrompt": "Things in Your Bathroom",
    "answer": "Showegel",
    "timestamp": "2026-02-22T16:49:48.380Z"
  },
  {
    "categoryId": 10,
    "categoryPrompt": "Best 90s Movies",
    "answer": "God father",
    "timestamp": "2026-02-22T16:50:11.489Z"
  },
  {
    "categoryId": 10,
    "categoryPrompt": "Best 90s Movies",
    "answer": "Avatar",
    "timestamp": "2026-02-22T16:50:23.482Z"
  },
  {
    "categoryId": 10,
    "categoryPrompt": "Best 90s Movies",
    "answer": "Shawsheng redemption",
    "timestamp": "2026-02-22T16:50:25.390Z"
  },
  {
    "categoryId": 10,
    "categoryPrompt": "Best 90s Movies",
    "answer": "Home alone",
    "timestamp": "2026-02-22T16:50:29.872Z"
  },
  {
    "categoryId": 22,
    "categoryPrompt": "Famous Comedy Actors",
    "answer": "Jonny depp",
    "timestamp": "2026-02-22T16:50:49.051Z"
  },
  {
    "categoryId": 22,
    "categoryPrompt": "Famous Comedy Actors",
    "answer": "Will smith",
    "timestamp": "2026-02-22T16:50:59.103Z"
  },
  {
    "categoryId": 3,
    "categoryPrompt": "Animated Movies Everyone Loves",
    "answer": "Forzen",
    "timestamp": "2026-02-22T16:51:21.847Z"
  },
  {
    "categoryId": 3,
    "categoryPrompt": "Animated Movies Everyone Loves",
    "answer": "Avatar",
    "timestamp": "2026-02-22T16:51:26.891Z"
  },
  {
    "categoryId": 38,
    "categoryPrompt": "Most Popular Cuisines in the World",
    "answer": "Italy",
    "timestamp": "2026-02-22T16:51:46.427Z"
  },
  {
    "categoryId": 29,
    "categoryPrompt": "Best Pop Singers",
    "answer": "Drake",
    "timestamp": "2026-02-22T16:52:00.375Z"
  },
  {
    "categoryId": 29,
    "categoryPrompt": "Best Pop Singers",
    "answer": "Jlo",
    "timestamp": "2026-02-22T16:52:05.133Z"
  },
  {
    "categoryId": 29,
    "categoryPrompt": "Best Pop Singers",
    "answer": "Bib",
    "timestamp": "2026-02-22T16:52:09.290Z"
  },
  {
    "categoryId": 20,
    "categoryPrompt": "Famous Actresses",
    "answer": "Jlo",
    "timestamp": "2026-02-22T16:52:24.546Z"
  },
  {
    "categoryId": 20,
    "categoryPrompt": "Famous Actresses",
    "answer": "Cameron Diaz",
    "timestamp": "2026-02-22T16:52:28.121Z"
  },
  {
    "categoryId": 20,
    "categoryPrompt": "Famous Actresses",
    "answer": "Jolya robertes",
    "timestamp": "2026-02-22T16:52:29.653Z"
  },
  {
    "categoryId": 20,
    "categoryPrompt": "Famous Actresses",
    "answer": "Jennifer aniston",
    "timestamp": "2026-02-22T16:52:34.998Z"
  },
  {
    "categoryId": 53,
    "categoryPrompt": "Best Cities to Visit",
    "answer": "Prague",
    "timestamp": "2026-02-22T16:52:58.637Z"
  },
  {
    "categoryId": 19,
    "categoryPrompt": "Most Famous Actors of All Time",
    "answer": "Albatichina",
    "timestamp": "2026-02-22T16:53:23.085Z"
  },
  {
    "categoryId": 19,
    "categoryPrompt": "Most Famous Actors of All Time",
    "answer": "Bradley cooper",
    "timestamp": "2026-02-22T16:53:29.200Z"
  },
  {
    "categoryId": 24,
    "categoryPrompt": "Actors Who Have Won the Most Oscars",
    "answer": "Will smith",
    "timestamp": "2026-02-22T16:53:50.151Z"
  },
  {
    "categoryId": 24,
    "categoryPrompt": "Actors Who Have Won the Most Oscars",
    "answer": "Albachini",
    "timestamp": "2026-02-22T16:54:00.875Z"
  },
  {
    "categoryId": 24,
    "categoryPrompt": "Actors Who Have Won the Most Oscars",
    "answer": "Morgan Freeman",
    "timestamp": "2026-02-22T16:54:09.361Z"
  }
]